odoo10_addon_l10n_br_account_payment_mode-10.0.1.0.0.99.dev8-py2.7-nspkg.pth
odoo/addons/l10n_br_account_payment_mode/README.rst
odoo/addons/l10n_br_account_payment_mode/__init__.py
odoo/addons/l10n_br_account_payment_mode/__manifest__.py
odoo/addons/l10n_br_account_payment_mode/demo/payment_demo.xml
odoo/addons/l10n_br_account_payment_mode/models/__init__.py
odoo/addons/l10n_br_account_payment_mode/models/payment_mode.py
odoo/addons/l10n_br_account_payment_mode/models/res_partner_bank.py
odoo/addons/l10n_br_account_payment_mode/static/description/icon.png
odoo/addons/l10n_br_account_payment_mode/views/account_invoice_view.xml
odoo/addons/l10n_br_account_payment_mode/views/payment_mode_view.xml
odoo10_addon_l10n_br_account_payment_mode-10.0.1.0.0.99.dev8.dist-info/METADATA
odoo10_addon_l10n_br_account_payment_mode-10.0.1.0.0.99.dev8.dist-info/RECORD
odoo10_addon_l10n_br_account_payment_mode-10.0.1.0.0.99.dev8.dist-info/WHEEL
odoo10_addon_l10n_br_account_payment_mode-10.0.1.0.0.99.dev8.dist-info/namespace_packages.txt
odoo10_addon_l10n_br_account_payment_mode-10.0.1.0.0.99.dev8.dist-info/top_level.txt
